keraTorch/__init__.py
keraTorch/_nbdev.py
keraTorch/activations.py
keraTorch/core.py
keraTorch/data.py
keraTorch/layers.py
keraTorch/losses.py
keraTorch/model.py
nbdev_template/__init__.py
nbdev_template/_nbdev.py
nbdev_template/core.py
nbdev_template/data.py
keraTorch-0.0.4.dist-info/LICENSE
keraTorch-0.0.4.dist-info/METADATA
keraTorch-0.0.4.dist-info/WHEEL
keraTorch-0.0.4.dist-info/entry_points.txt
keraTorch-0.0.4.dist-info/top_level.txt
keraTorch-0.0.4.dist-info/RECORD
